napari_orientationpy/__init__.py
napari_orientationpy/__main__.py
napari_orientationpy/_version.py
napari_orientationpy/_widget.py
napari_orientationpy/misorientation.py
napari_orientationpy/napari.yaml
napari_orientationpy-0.1.1.dist-info/licenses/LICENSE
napari_orientationpy-0.1.1.dist-info/METADATA
napari_orientationpy-0.1.1.dist-info/WHEEL
napari_orientationpy-0.1.1.dist-info/entry_points.txt
napari_orientationpy-0.1.1.dist-info/top_level.txt
napari_orientationpy-0.1.1.dist-info/RECORD
