Metadata-Version: 2.4
Name: napari-orientationpy
Version: 0.1.1
Summary: Napari plugin for OrientationPy.
Author-email: EPFL Center for Imaging <imaging@epfl.ch>
License: Copyright (c) 2024, EPFL
Project-URL: homepage, https://github.com/EPFL-Center-for-Imaging/napari-orientationpy
Project-URL: repository, https://github.com/EPFL-Center-for-Imaging/napari-orientationpy
Classifier: Development Status :: 2 - Pre-Alpha
Classifier: License :: OSI Approved :: BSD License
Classifier: Programming Language :: Python :: 3
Classifier: Programming Language :: Python :: 3.9
Classifier: Programming Language :: Python :: 3.10
Classifier: Programming Language :: Python :: 3.11
Classifier: Programming Language :: Python :: 3.12
Classifier: Topic :: Scientific/Engineering :: Image Processing
Requires-Python: >=3.9
License-File: LICENSE
Requires-Dist: napari[all]>=0.4.16
Requires-Dist: qtpy
Requires-Dist: orientationpy>=0.3.0
Requires-Dist: numpy
Requires-Dist: pandas
Requires-Dist: matplotlib
Requires-Dist: scikit-image
Dynamic: license-file
